CHANGELOG.txt
LICENSE
LICENSE.txt
MANIFEST.in
README.md
setup.py
test.py
discord-helpers/__init__.py
discord-helpers/moderation/ban.py
discordopcogsext.egg-info/PKG-INFO
discordopcogsext.egg-info/SOURCES.txt
discordopcogsext.egg-info/dependency_links.txt
discordopcogsext.egg-info/requires.txt
discordopcogsext.egg-info/top_level.txt
env/bin/rst2html.py
env/bin/rst2html4.py
env/bin/rst2html5.py
env/bin/rst2latex.py
env/bin/rst2man.py
env/bin/rst2odt.py
env/bin/rst2odt_prepstyles.py
env/bin/rst2pseudoxml.py
env/bin/rst2s5.py
env/bin/rst2xetex.py
env/bin/rst2xml.py
env/bin/rstpep2html.py
env/lib/python3.9/site-packages/pyparsing.py
env/lib/python3.9/site-packages/six.py
env/lib/python3.9/site-packages/zipp.py
env/lib/python3.9/site-packages/Pygments-2.9.0.dist-info/entry_points.txt
env/lib/python3.9/site-packages/Pygments-2.9.0.dist-info/top_level.txt
env/lib/python3.9/site-packages/_distutils_hack/__init__.py
env/lib/python3.9/site-packages/_distutils_hack/override.py
env/lib/python3.9/site-packages/bleach/__init__.py
env/lib/python3.9/site-packages/bleach/callbacks.py
env/lib/python3.9/site-packages/bleach/html5lib_shim.py
env/lib/python3.9/site-packages/bleach/linkifier.py
env/lib/python3.9/site-packages/bleach/sanitizer.py
env/lib/python3.9/site-packages/bleach/utils.py
env/lib/python3.9/site-packages/bleach-3.3.0.dist-info/top_level.txt
env/lib/python3.9/site-packages/bleach/_vendor/__init__.py
env/lib/python3.9/site-packages/bleach/_vendor/vendor.txt
env/lib/python3.9/site-packages/bleach/_vendor/Django-1.11.29.dist-info/entry_points.txt
env/lib/python3.9/site-packages/bleach/_vendor/Django-1.11.29.dist-info/top_level.txt
env/lib/python3.9/site-packages/bleach/_vendor/django/__init__.py
env/lib/python3.9/site-packages/bleach/_vendor/django/core/__init__.py
env/lib/python3.9/site-packages/bleach/_vendor/django/core/validators.py
env/lib/python3.9/site-packages/bleach/_vendor/html5lib/__init__.py
env/lib/python3.9/site-packages/bleach/_vendor/html5lib/_ihatexml.py
env/lib/python3.9/site-packages/bleach/_vendor/html5lib/_inputstream.py
env/lib/python3.9/site-packages/bleach/_vendor/html5lib/_tokenizer.py
env/lib/python3.9/site-packages/bleach/_vendor/html5lib/_utils.py
env/lib/python3.9/site-packages/bleach/_vendor/html5lib/constants.py
env/lib/python3.9/site-packages/bleach/_vendor/html5lib/html5parser.py
env/lib/python3.9/site-packages/bleach/_vendor/html5lib/serializer.py
env/lib/python3.9/site-packages/bleach/_vendor/html5lib-1.1.dist-info/top_level.txt
env/lib/python3.9/site-packages/bleach/_vendor/html5lib/_trie/__init__.py
env/lib/python3.9/site-packages/bleach/_vendor/html5lib/_trie/_base.py
env/lib/python3.9/site-packages/certifi-2021.5.30.dist-info/top_level.txt
env/lib/python3.9/site-packages/chardet-4.0.0.dist-info/entry_points.txt
env/lib/python3.9/site-packages/chardet-4.0.0.dist-info/top_level.txt
env/lib/python3.9/site-packages/colorama-0.4.4.dist-info/LICENSE.txt
env/lib/python3.9/site-packages/colorama-0.4.4.dist-info/top_level.txt
env/lib/python3.9/site-packages/discordopcogsext-0.0.1-py3.9.egg-info/SOURCES.txt
env/lib/python3.9/site-packages/discordopcogsext-0.0.1-py3.9.egg-info/dependency_links.txt
env/lib/python3.9/site-packages/discordopcogsext-0.0.1-py3.9.egg-info/installed-files.txt
env/lib/python3.9/site-packages/discordopcogsext-0.0.1-py3.9.egg-info/top_level.txt
env/lib/python3.9/site-packages/docutils-0.17.1.dist-info/COPYING.txt
env/lib/python3.9/site-packages/docutils-0.17.1.dist-info/top_level.txt
env/lib/python3.9/site-packages/idna-2.10.dist-info/top_level.txt
env/lib/python3.9/site-packages/importlib_metadata-4.5.0.dist-info/top_level.txt
env/lib/python3.9/site-packages/keyring-23.0.1.dist-info/entry_points.txt
env/lib/python3.9/site-packages/keyring-23.0.1.dist-info/top_level.txt
env/lib/python3.9/site-packages/packaging-20.9.dist-info/top_level.txt
env/lib/python3.9/site-packages/pip-21.1.1.dist-info/LICENSE.txt
env/lib/python3.9/site-packages/pip-21.1.1.dist-info/entry_points.txt
env/lib/python3.9/site-packages/pip-21.1.1.dist-info/top_level.txt
env/lib/python3.9/site-packages/pkginfo-1.7.0.dist-info/LICENSE.txt
env/lib/python3.9/site-packages/pkginfo-1.7.0.dist-info/entry_points.txt
env/lib/python3.9/site-packages/pkginfo-1.7.0.dist-info/top_level.txt
env/lib/python3.9/site-packages/pyparsing-2.4.7.dist-info/top_level.txt
env/lib/python3.9/site-packages/readme_renderer-29.0.dist-info/entry_points.txt
env/lib/python3.9/site-packages/readme_renderer-29.0.dist-info/top_level.txt
env/lib/python3.9/site-packages/requests-2.25.1.dist-info/top_level.txt
env/lib/python3.9/site-packages/requests_toolbelt-0.9.1.dist-info/top_level.txt
env/lib/python3.9/site-packages/rfc3986-1.5.0.dist-info/top_level.txt
env/lib/python3.9/site-packages/setuptools-56.0.0.dist-info/dependency_links.txt
env/lib/python3.9/site-packages/setuptools-56.0.0.dist-info/entry_points.txt
env/lib/python3.9/site-packages/setuptools-56.0.0.dist-info/top_level.txt
env/lib/python3.9/site-packages/six-1.16.0.dist-info/top_level.txt
env/lib/python3.9/site-packages/tqdm-4.61.0.dist-info/entry_points.txt
env/lib/python3.9/site-packages/tqdm-4.61.0.dist-info/top_level.txt
env/lib/python3.9/site-packages/twine-3.4.1.dist-info/entry_points.txt
env/lib/python3.9/site-packages/twine-3.4.1.dist-info/top_level.txt
env/lib/python3.9/site-packages/urllib3-1.26.5.dist-info/LICENSE.txt
env/lib/python3.9/site-packages/urllib3-1.26.5.dist-info/top_level.txt
env/lib/python3.9/site-packages/webencodings-0.5.1.dist-info/top_level.txt
env/lib/python3.9/site-packages/zipp-3.4.1.dist-info/top_level.txt